flywheel_transfer_smartcopy/.DS_Store
flywheel_transfer_smartcopy/SmartCopier.py
flywheel_transfer_smartcopy/__init__.py
flywheel_transfer_smartcopy-0.3.5.dist-info/LICENSE
flywheel_transfer_smartcopy-0.3.5.dist-info/METADATA
flywheel_transfer_smartcopy-0.3.5.dist-info/WHEEL
flywheel_transfer_smartcopy-0.3.5.dist-info/RECORD
