Metadata-Version: 2.1
Name: flywheel-transfer-smartcopy
Version: 0.3.5
Summary: smart copy utility
Author: David Parker
Author-email: davidparker@flywheel.io
Requires-Python: >=3.12,<4.0
Classifier: Programming Language :: Python :: 3
Classifier: Programming Language :: Python :: 3.12
Requires-Dist: flywheel-transfer-utils (>=0.2.4,<0.3.0)
Requires-Dist: fw-client (>=0.8.6,<0.9.0)
